app/__init__.py
app/main.py
app/raw.py
pypipex-0.0.5.dist-info/licenses/LICENSE
src/__init__.py
src/modules/__init__.py
src/modules/io_transforms.py
src/modules/raw_transforms.py
src/modules/wordcount_minimal.py
src/queries/__init__.py
tests/__init__.py
pypipex-0.0.5.dist-info/METADATA
pypipex-0.0.5.dist-info/WHEEL
pypipex-0.0.5.dist-info/entry_points.txt
pypipex-0.0.5.dist-info/top_level.txt
pypipex-0.0.5.dist-info/RECORD
