Metadata-Version: 2.4
Name: pypipex
Version: 0.0.5
Summary: A Data Pipeline Framework using Apache Beam Pipelines, adding PTransforms and utility functions.
Author: israelmartinez.data.engineer@gmail.com
Requires-Python: >=3.8
License-File: LICENSE
Requires-Dist: apache-beam[gcp]==2.65.0
Dynamic: author
Dynamic: license-file
Dynamic: requires-dist
Dynamic: requires-python
Dynamic: summary
